rest_client/__init__.py
rest_client/auth.py
rest_client/conf.py
rest_client/exception.py
rest_client/resources.py
rest_client/utils.py
rest_client/validator.py
universal_rest_client-2.3.5.dist-info/LICENSE
universal_rest_client-2.3.5.dist-info/METADATA
universal_rest_client-2.3.5.dist-info/WHEEL
universal_rest_client-2.3.5.dist-info/top_level.txt
universal_rest_client-2.3.5.dist-info/RECORD
