Metadata-Version: 2.1
Name: universal-rest-client
Version: 2.3.5
Summary: A generic python REST client
Home-page: https://bitbucket.org/nhm_bioinformatics/qrest/
Author: Joris Benschop (BASF Vegetable Seeds)
Author-email: joris.benschop@gmail.com
Maintainer: Joris Benschop
Maintainer-email: joris.benschop@gmail.com
License: GPLv3
Keywords: generic REST API client
Platform: UNKNOWN
Classifier: Development Status :: 4 - Beta
Classifier: Intended Audience :: Information Technology
Classifier: Topic :: Software Development :: Libraries :: Python Modules
Classifier: License :: OSI Approved :: GNU General Public License v3 (GPLv3)
Classifier: Programming Language :: Python :: 2
Classifier: Programming Language :: Python :: 2.7
Classifier: Programming Language :: Python :: 3
Classifier: Programming Language :: Python :: 3.4
Classifier: Programming Language :: Python :: 3.5
Classifier: Programming Language :: Python :: 3.6
Classifier: Programming Language :: Python :: 3.7
Requires-Dist: requests
Requires-Dist: six
Requires-Dist: uritools
Requires-Dist: PyContracts
Provides-Extra: dev
Requires-Dist: Sphinx ; extra == 'dev'
Provides-Extra: test
Requires-Dist: requests-mock ; extra == 'test'
